<?xml version="1.0" encoding="UTF-8" standalone="yes"?><data><clientes><cliente><id>CLI-111</id><nombre>Juan Nuñez</nombre><telefono>121212</telefono><email>juan@gmail.com</email><descuento>2.0</descuento></cliente><cliente><id>CLI-003</id><nombre>Pedro Fernandez</nombre><telefono>433455</telefono><email>pedro@gmail.com</email><descuento>1.0</descuento></cliente><cliente><id>123</id><nombre>abc</nombre><telefono>88</telefono><email>abc@gmail.com</email><descuento>0.0</descuento></cliente><cliente><id>CLI-456</id><nombre>Vicente Fernandez</nombre><telefono>45466</telefono><email>chente@gmail.com</email><descuento>0.0</descuento></cliente></clientes><cajero><cajero><id>12354</id><nombre>José Guevara</nombre></cajero><cajero><id>23456</id><nombre>Laura Brenes</nombre></cajero></cajero><productos><producto><codigo>0101</codigo><descripcion>Agua</descripcion><precio>5.0</precio><categoria><id>002</id><nombre>Agua</nombre></categoria><unidad>Botella</unidad><existencia>0</existencia></producto><producto><codigo>2345</codigo><descripcion>Brownie</descripcion><precio>1200.0</precio><categoria><id>003</id><nombre>Dulce</nombre></categoria><unidad>Bolsa</unidad><existencia>0</existencia></producto><producto><codigo>2233</codigo><descripcion>Hersheys</descripcion><precio>400.0</precio><categoria><id>003</id><nombre>Dulce</nombre></categoria><unidad>Barra</unidad><existencia>0</existencia></producto><producto><codigo>1234</codigo><descripcion>vinito_fino</descripcion><precio>1000.5</precio><categoria><id>004</id><nombre>Vino</nombre></categoria><unidad>Botella</unidad><existencia>0</existencia></producto></productos><categorias/><lineas/><facturas/><fechas/><lineasHistoricas/></data>